[
  {
    "id": "1",
    "name": "CSW HMDK Summary",
    "url": "http://metaver.de/csw?service=CSW&version=2.0.2&request=GetRecordById&typeNames=csw:Record&elementsetname=summary",
    "typ": "CSW"
  },
  {
    "id" : "2",
    "name" : "Metadaten-URL",
    "url" : "http://metaver.de/trefferanzeige?docuuid=",
    "typ" : "URL"
  },
  {
    "id": "3",
    "name": "CSW HMDK Full",
    "url": "http://metaver.de/csw?service=CSW&version=2.0.2&request=GetRecordById&typeNames=csw:Record&elementsetname=full",
    "typ": "CSW"
  },
  {
    "id" : "11",
    "name" : "Komoot Photon Suche",
    "url" : "https://photon.komoot.io/api/?",
    "typ" : "WFS"
  },
  {
    "id" : "80002",
    "name" : "Email Service by PHP",
    "url" : "https://geoportal-hamburg.de/smtp/sendmail.php",
    "typ" : "EmailService"
  },
  {
    "id" : "streetsmart",
    "name" : "StreetSmart",
    "url" : "https://atlas.cyclomedia.com/",
    "typ" : "StreeSmartApi",
    "params": {
      "username": "markus.besenfelder@gv.hamburg.de",
      "password": "s.hKKA-EtusCd[F",
      "apiKey": "aT4J6745OrAliTstanAJmTU1yfwNyPQhuLM5aP0ZarYFuvsR2Dg12nANy7c9ar0Z",
      "xxxsrs": "EPSG:25832",
      "locale": "de"
    }
  }
]
